purus/__init__.py
purus/amazon_cloudfront.py
purus/errors.py
purus-0.1.1.dist-info/LICENSE
purus-0.1.1.dist-info/WHEEL
purus-0.1.1.dist-info/METADATA
purus-0.1.1.dist-info/RECORD
