Metadata-Version: 2.1
Name: purus
Version: 0.1.1
Summary: parse parameters
Home-page: https://github.com/acxelerator/purus
License: MIT
Keywords: aws,parameters,parser
Author: acxelerator
Author-email: acx0911@gmail.com
Requires-Python: >=3.8,<3.11
Classifier: License :: OSI Approved :: MIT License
Classifier: Programming Language :: Python :: 3
Classifier: Programming Language :: Python :: 3.8
Classifier: Programming Language :: Python :: 3.9
Classifier: Programming Language :: Python :: 3.10
Project-URL: Repository, https://github.com/acxelerator/purus
